[
  {
    "title": "Macbook Pro Retina 15\" i7 2.6 / 8Gb DDR3 / 512 SSD / GT 650M 1Gb",
    "link": "https://pr.olx.com.br/regiao-de-curitiba-e-paranagua?q=macbook%20pro",
    "image": "https://img.olx.com.br/thumbs256x256/97/977219367478635.jpg",
    "price": "R$ 3.950"
  },
  {
    "title": "Macbook Pro 13pol - 6GB ram - SSD - Excelente",
    "link": "https://pr.olx.com.br/regiao-de-curitiba-e-paranagua?q=macbook%20pro",
    "image": "https://img.olx.com.br/thumbs256x256/83/832159476038022.jpg",
    "price": "R$ 2.399"
  },
  {},
  {
    "link": "https://pr.olx.com.br/regiao-de-curitiba-e-paranagua?q=macbook%20pro",
    "image": "https://s.yimg.com/cv/apiv2/adbuilder/gemini.png"
  },
  {
    "link": "https://pr.olx.com.br/regiao-de-curitiba-e-paranagua?q=macbook%20pro",
    "image": "https://s.yimg.com/cv/apiv2/adbuilder/gemini.png"
  },
  {
    "title": " macbook pro 2010 15\" 6gb ssd",
    "link": "https://pr.olx.com.br/regiao-de-curitiba-e-paranagua?q=macbook%20pro",
    "image": "https://img.olx.com.br/thumbs256x256/97/976226362537501.jpg",
    "price": "R$ 1.900"
  },
  {
    "title": "MacBook Pro A1502 Late 2013 (retina)",
    "link": "https://pr.olx.com.br/regiao-de-curitiba-e-paranagua?q=macbook%20pro",
    "image": "https://img.olx.com.br/thumbs256x256/64/649141239185281.jpg",
    "price": "R$ 3.150"
  },
  {
    "title": "MacBook Pro",
    "link": "https://pr.olx.com.br/regiao-de-curitiba-e-paranagua?q=macbook%20pro",
    "image": "https://img.olx.com.br/thumbs256x256/90/902107830385725.jpg",
    "price": "R$ 1.000"
  },
  {
    "link": "https://pr.olx.com.br/regiao-de-curitiba-e-paranagua?q=macbook%20pro",
    "image": "https://s.yimg.com/cv/apiv2/adbuilder/gemini.png"
  },
  {
    "link": "https://pr.olx.com.br/regiao-de-curitiba-e-paranagua?q=macbook%20pro",
    "image": "https://s.yimg.com/cv/apiv2/adbuilder/gemini.png"
  },
  {
    "title": "MacBook Pro 2012 - i5 - SSD 120GB - 4GB - Loja Física",
    "link": "https://pr.olx.com.br/regiao-de-curitiba-e-paranagua?q=macbook%20pro",
    "image": "https://img.olx.com.br/thumbs256x256/09/094208722509554.jpg",
    "price": "R$ 2.890"
  },
  {
    "title": "MacBook Pro 2015 Retina | 13,3' | 256GB | Bateria Nova",
    "link": "https://pr.olx.com.br/regiao-de-curitiba-e-paranagua?q=macbook%20pro",
    "image": "https://img.olx.com.br/thumbs256x256/00/005220247144662.jpg",
    "price": "R$ 3.690"
  },
  {
    "title": "MacBook Pro (13 2012",
    "link": "https://pr.olx.com.br/regiao-de-curitiba-e-paranagua?q=macbook%20pro",
    "image": "https://img.olx.com.br/thumbs256x256/30/308189818728216.jpg",
    "price": "R$ 3.500"
  },
  {
    "title": "Macbook Pro 15\"",
    "link": "https://pr.olx.com.br/regiao-de-curitiba-e-paranagua?q=macbook%20pro",
    "image": "https://img.olx.com.br/thumbs256x256/09/090242360655311.jpg",
    "price": "R$ 8.887"
  },
  {
    "title": "Macbook Pro 13 Touchbar - 512gb Ssd",
    "link": "https://pr.olx.com.br/regiao-de-curitiba-e-paranagua?q=macbook%20pro",
    "image": "https://img.olx.com.br/thumbs256x256/09/096270129222584.jpg",
    "price": "R$ 6.500"
  },
  {},
  {
    "title": "MacBook Pro retina 2017 i5 8GB SSD 1TB",
    "link": "https://pr.olx.com.br/regiao-de-curitiba-e-paranagua?q=macbook%20pro",
    "image": "https://img.olx.com.br/thumbs256x256/09/092204249207195.jpg",
    "price": "R$ 6.100"
  },
  {
    "title": "Macbook Pro 16\" Touchbar 2019 I9/16GB/1TB Ssd",
    "link": "https://pr.olx.com.br/regiao-de-curitiba-e-paranagua?q=macbook%20pro",
    "image": "https://img.olx.com.br/thumbs256x256/09/093216245810562.jpg",
    "price": "R$ 16.000"
  },
  {
    "title": "MacBook Pro M1 2021 512 Gb Lacrado",
    "link": "https://pr.olx.com.br/regiao-de-curitiba-e-paranagua?q=macbook%20pro",
    "image": "https://img.olx.com.br/thumbs256x256/03/036214002203059.jpg",
    "price": "R$ 14.999"
  },
  {
    "title": "MacBook Pro Retina 2014",
    "link": "https://pr.olx.com.br/regiao-de-curitiba-e-paranagua?q=macbook%20pro",
    "image": "https://img.olx.com.br/thumbs256x256/09/094237129222519.jpg",
    "price": "R$ 3.500"
  },
  {
    "title": "MacBook Pro M1 2020 ",
    "link": "https://pr.olx.com.br/regiao-de-curitiba-e-paranagua?q=macbook%20pro",
    "image": "https://img.olx.com.br/thumbs256x256/09/092273125778962.jpg",
    "price": "R$ 7.899"
  },
  {
    "title": "Macbook Pro Impecável",
    "link": "https://pr.olx.com.br/regiao-de-curitiba-e-paranagua?q=macbook%20pro",
    "image": "data:image/gif;base64,R0lGODlhAQABAAD/ACwAAAAAAQABAAACADs=",
    "price": "R$ 2.200"
  },
  {
    "title": "MacBook Pro 2016 SSD 256gb ",
    "link": "https://pr.olx.com.br/regiao-de-curitiba-e-paranagua?q=macbook%20pro",
    "image": "data:image/gif;base64,R0lGODlhAQABAAD/ACwAAAAAAQABAAACADs=",
    "price": "R$ 5.999"
  },
  {
    "title": "Macbook Pro ",
    "link": "https://pr.olx.com.br/regiao-de-curitiba-e-paranagua?q=macbook%20pro",
    "image": "data:image/gif;base64,R0lGODlhAQABAAD/ACwAAAAAAQABAAACADs=",
    "price": "R$ 2.850"
  },
  {
    "title": "Macbook Pro 2017 - Intel Core I5 Dual Core 8gb",
    "link": "https://pr.olx.com.br/regiao-de-curitiba-e-paranagua?q=macbook%20pro",
    "image": "data:image/gif;base64,R0lGODlhAQABAAD/ACwAAAAAAQABAAACADs=",
    "price": "R$ 6.199"
  },
  {
    "title": "MacBook Pro 13\" Intel Core i7, 8GB Memória DD3 e 750 GB de HD",
    "link": "https://pr.olx.com.br/regiao-de-curitiba-e-paranagua?q=macbook%20pro",
    "image": "data:image/gif;base64,R0lGODlhAQABAAD/ACwAAAAAAQABAAACADs=",
    "price": "R$ 3.245"
  },
  {
    "title": "MacBook Pro",
    "link": "https://pr.olx.com.br/regiao-de-curitiba-e-paranagua?q=macbook%20pro",
    "image": "data:image/gif;base64,R0lGODlhAQABAAD/ACwAAAAAAQABAAACADs=",
    "price": "R$ 3.200"
  },
  {
    "title": "Macbook Pro 16gb RAM, 480 SSD + 500 HD",
    "link": "https://pr.olx.com.br/regiao-de-curitiba-e-paranagua?q=macbook%20pro",
    "image": "data:image/gif;base64,R0lGODlhAQABAAD/ACwAAAAAAQABAAACADs=",
    "price": "R$ 2.200"
  },
  {},
  {
    "title": "Macbook Pro 13\"em Ótimo Estado",
    "link": "https://pr.olx.com.br/regiao-de-curitiba-e-paranagua?q=macbook%20pro",
    "image": "data:image/gif;base64,R0lGODlhAQABAAD/ACwAAAAAAQABAAACADs=",
    "price": "R$ 2.450"
  },
  {
    "title": "MacBook Pro Retina 13' Intel i5 ",
    "link": "https://pr.olx.com.br/regiao-de-curitiba-e-paranagua?q=macbook%20pro",
    "image": "data:image/gif;base64,R0lGODlhAQABAAD/ACwAAAAAAQABAAACADs=",
    "price": "R$ 3.200"
  },
  {
    "title": "MacBook Pro 2012 13' Polegadas",
    "link": "https://pr.olx.com.br/regiao-de-curitiba-e-paranagua?q=macbook%20pro",
    "image": "data:image/gif;base64,R0lGODlhAQABAAD/ACwAAAAAAQABAAACADs=",
    "price": "R$ 3.450"
  },
  {
    "title": "Macbook PRO Retina 13\" 2015",
    "link": "https://pr.olx.com.br/regiao-de-curitiba-e-paranagua?q=macbook%20pro",
    "image": "data:image/gif;base64,R0lGODlhAQABAAD/ACwAAAAAAQABAAACADs=",
    "price": "R$ 4.000"
  },
  {
    "title": "Macbook Pro 13 M1 8gb 256gb Apple A2338 Novo Lacrado",
    "link": "https://pr.olx.com.br/regiao-de-curitiba-e-paranagua?q=macbook%20pro",
    "image": "data:image/gif;base64,R0lGODlhAQABAAD/ACwAAAAAAQABAAACADs=",
    "price": "R$ 8.690"
  },
  {
    "title": "  Macbook Pro 2012. Intel i5. Mem. 8 GB. SSD 240 GB. Até 12x no Cartão",
    "link": "https://pr.olx.com.br/regiao-de-curitiba-e-paranagua?q=macbook%20pro",
    "image": "data:image/gif;base64,R0lGODlhAQABAAD/ACwAAAAAAQABAAACADs=",
    "price": "R$ 2.899"
  },
  {
    "title": "MacBook Pro (13 polegadas, 2019) Cinza Espacial (Space Gray). Troco",
    "link": "https://pr.olx.com.br/regiao-de-curitiba-e-paranagua?q=macbook%20pro",
    "image": "data:image/gif;base64,R0lGODlhAQABAAD/ACwAAAAAAQABAAACADs=",
    "price": "R$ 7.999"
  },
  {
    "title": "MacBook Pro (16 polegadas, 2019) Aceito Troca.",
    "link": "https://pr.olx.com.br/regiao-de-curitiba-e-paranagua?q=macbook%20pro",
    "image": "data:image/gif;base64,R0lGODlhAQABAAD/ACwAAAAAAQABAAACADs=",
    "price": "R$ 13.999"
  },
  {
    "title": "Macbook Pro (13-inch, M1, 2020)",
    "link": "https://pr.olx.com.br/regiao-de-curitiba-e-paranagua?q=macbook%20pro",
    "image": "data:image/gif;base64,R0lGODlhAQABAAD/ACwAAAAAAQABAAACADs=",
    "price": "R$ 10.000"
  },
  {
    "title": "macbook pro (13-inch, early 2011) - 2,3 ghz intel core I5 - 4gb ram 128gb ssd",
    "link": "https://pr.olx.com.br/regiao-de-curitiba-e-paranagua?q=macbook%20pro",
    "image": "data:image/gif;base64,R0lGODlhAQABAAD/ACwAAAAAAQABAAACADs=",
    "price": "R$ 3.500"
  },
  {},
  {
    "title": "Macbook Pro 2016 (Lindo)",
    "link": "https://pr.olx.com.br/regiao-de-curitiba-e-paranagua?q=macbook%20pro",
    "image": "data:image/gif;base64,R0lGODlhAQABAAD/ACwAAAAAAQABAAACADs=",
    "price": "R$ 5.000"
  },
  {
    "title": "MacBook Pro M1 512 Gb - Lacrados -12x no cartão - Nota fiscal ",
    "link": "https://pr.olx.com.br/regiao-de-curitiba-e-paranagua?q=macbook%20pro",
    "image": "data:image/gif;base64,R0lGODlhAQABAAD/ACwAAAAAAQABAAACADs=",
    "price": "R$ 10.699"
  },
  {
    "title": "Macbook pro core i7 8 gigas ssd 120 gigas impecável $3590,00",
    "link": "https://pr.olx.com.br/regiao-de-curitiba-e-paranagua?q=macbook%20pro",
    "image": "data:image/gif;base64,R0lGODlhAQABAAD/ACwAAAAAAQABAAACADs=",
    "price": "R$ 3.590"
  },
  {
    "title": "MacBook Pro 16gb de ram",
    "link": "https://pr.olx.com.br/regiao-de-curitiba-e-paranagua?q=macbook%20pro",
    "image": "data:image/gif;base64,R0lGODlhAQABAAD/ACwAAAAAAQABAAACADs=",
    "price": "R$ 11.500"
  },
  {
    "title": "Macbook pro 13",
    "link": "https://pr.olx.com.br/regiao-de-curitiba-e-paranagua?q=macbook%20pro",
    "image": "data:image/gif;base64,R0lGODlhAQABAAD/ACwAAAAAAQABAAACADs=",
    "price": "R$ 2.600"
  },
  {
    "title": "Macbook Pro 2019 Touchbar i5 8gb 128gb SSD - Estado de novo - Confira",
    "link": "https://pr.olx.com.br/regiao-de-curitiba-e-paranagua?q=macbook%20pro",
    "image": "data:image/gif;base64,R0lGODlhAQABAAD/ACwAAAAAAQABAAACADs=",
    "price": "R$ 6.999"
  },
  {
    "title": "MacBook Pro 2011 Tela 13 ",
    "link": "https://pr.olx.com.br/regiao-de-curitiba-e-paranagua?q=macbook%20pro",
    "image": "data:image/gif;base64,R0lGODlhAQABAAD/ACwAAAAAAQABAAACADs=",
    "price": "R$ 2.300"
  },
  {
    "title": "MacBook Pro M1 256 Gb - Lacrado - 12x no cartão - Nota fiscal - Loja.",
    "link": "https://pr.olx.com.br/regiao-de-curitiba-e-paranagua?q=macbook%20pro",
    "image": "data:image/gif;base64,R0lGODlhAQABAAD/ACwAAAAAAQABAAACADs=",
    "price": "R$ 8.999"
  },
  {
    "title": " Macbook Pro 2015. Tela Retina. Intel i5. SSD 240 GB. Mem. 8 GB. Pronta Entrega.",
    "link": "https://pr.olx.com.br/regiao-de-curitiba-e-paranagua?q=macbook%20pro",
    "image": "data:image/gif;base64,R0lGODlhAQABAAD/ACwAAAAAAQABAAACADs=",
    "price": "R$ 4.298"
  },
  {
    "title": "MacBook PRO Catalina (13-inch, Mid 2012)",
    "link": "https://pr.olx.com.br/regiao-de-curitiba-e-paranagua?q=macbook%20pro",
    "image": "data:image/gif;base64,R0lGODlhAQABAAD/ACwAAAAAAQABAAACADs=",
    "price": "R$ 2.800"
  },
  {
    "title": "MacBook Pro Retina 2014 de 15 poleg model A1398 i7 16gb SSD 256gb Seminovo Ótimo Investim",
    "link": "https://pr.olx.com.br/regiao-de-curitiba-e-paranagua?q=macbook%20pro",
    "image": "data:image/gif;base64,R0lGODlhAQABAAD/ACwAAAAAAQABAAACADs=",
    "price": "R$ 6.500"
  },
  {
    "title": "Macbook Pro 2017 Space Gray",
    "link": "https://pr.olx.com.br/regiao-de-curitiba-e-paranagua?q=macbook%20pro",
    "image": "data:image/gif;base64,R0lGODlhAQABAAD/ACwAAAAAAQABAAACADs=",
    "price": "R$ 7.500"
  },
  {
    "title": "MacBook Pro i9 Apple Space Gray ",
    "link": "https://pr.olx.com.br/regiao-de-curitiba-e-paranagua?q=macbook%20pro",
    "image": "data:image/gif;base64,R0lGODlhAQABAAD/ACwAAAAAAQABAAACADs=",
    "price": "R$ 11.900"
  },
  {
    "title": "Macbook Pro. Tela de Retina 15. Intel i7. Mem. 16 GB. SSD 751 GB. Até 12 no cartão",
    "link": "https://pr.olx.com.br/regiao-de-curitiba-e-paranagua?q=macbook%20pro",
    "image": "data:image/gif;base64,R0lGODlhAQABAAD/ACwAAAAAAQABAAACADs=",
    "price": "R$ 4.398"
  },
  {
    "title": "MacBook Pro 13 2017. (i7/16gb/512ssd). Novo. Troco",
    "link": "https://pr.olx.com.br/regiao-de-curitiba-e-paranagua?q=macbook%20pro",
    "image": "data:image/gif;base64,R0lGODlhAQABAAD/ACwAAAAAAQABAAACADs=",
    "price": "R$ 8.499"
  },
  {
    "title": "MacBook Pro 2017 13 polegadas com Magic Mouse e keyboard ",
    "link": "https://pr.olx.com.br/regiao-de-curitiba-e-paranagua?q=macbook%20pro",
    "image": "data:image/gif;base64,R0lGODlhAQABAAD/ACwAAAAAAQABAAACADs=",
    "price": "R$ 8.000"
  },
  {
    "title": "MacBook Pro (Retina, 13-inch, Mid 2014)",
    "link": "https://pr.olx.com.br/regiao-de-curitiba-e-paranagua?q=macbook%20pro",
    "image": "data:image/gif;base64,R0lGODlhAQABAAD/ACwAAAAAAQABAAACADs=",
    "price": "R$ 5.500"
  },
  {
    "title": "MacBook Pro M1 256 Gb - Lacrado - 12x no cartão - Nota fiscal - Loja.",
    "link": "https://pr.olx.com.br/regiao-de-curitiba-e-paranagua?q=macbook%20pro",
    "image": "data:image/gif;base64,R0lGODlhAQABAAD/ACwAAAAAAQABAAACADs=",
    "price": ""
  }
]